ros_rosidl_core_runtime-0.3.1.data/data/share/ament_index/resource_index/package_run_dependencies/rosidl_core_runtime
ros_rosidl_core_runtime-0.3.1.data/data/share/ament_index/resource_index/packages/rosidl_core_runtime
ros_rosidl_core_runtime-0.3.1.data/data/share/ament_index/resource_index/parent_prefix_path/rosidl_core_runtime
ros_rosidl_core_runtime-0.3.1.data/data/share/rosidl_core_runtime/local_setup.bash
ros_rosidl_core_runtime-0.3.1.data/data/share/rosidl_core_runtime/local_setup.dsv
ros_rosidl_core_runtime-0.3.1.data/data/share/rosidl_core_runtime/local_setup.sh
ros_rosidl_core_runtime-0.3.1.data/data/share/rosidl_core_runtime/local_setup.zsh
ros_rosidl_core_runtime-0.3.1.data/data/share/rosidl_core_runtime/package.dsv
ros_rosidl_core_runtime-0.3.1.data/data/share/rosidl_core_runtime/package.xml
ros_rosidl_core_runtime-0.3.1.data/data/share/rosidl_core_runtime/cmake/rosidl_core_runtime-extras.cmake
ros_rosidl_core_runtime-0.3.1.data/data/share/rosidl_core_runtime/cmake/rosidl_core_runtimeConfig-version.cmake
ros_rosidl_core_runtime-0.3.1.data/data/share/rosidl_core_runtime/cmake/rosidl_core_runtimeConfig.cmake
ros_rosidl_core_runtime-0.3.1.data/data/share/rosidl_core_runtime/environment/ament_prefix_path.dsv
ros_rosidl_core_runtime-0.3.1.data/data/share/rosidl_core_runtime/environment/ament_prefix_path.sh
ros_rosidl_core_runtime-0.3.1.data/data/share/rosidl_core_runtime/environment/path.dsv
ros_rosidl_core_runtime-0.3.1.data/data/share/rosidl_core_runtime/environment/path.sh
rosidl_core_runtime/_dummy.cpython-313-x86_64-linux-gnu.so
ros_rosidl_core_runtime-0.3.1.dist-info/METADATA
ros_rosidl_core_runtime-0.3.1.dist-info/WHEEL
ros_rosidl_core_runtime-0.3.1.dist-info/top_level.txt
ros_rosidl_core_runtime-0.3.1.dist-info/RECORD
