Metadata-Version: 2.4
Name: ros-rosidl-core-runtime
Version: 0.3.1
Summary: A core ROS package that provides runtime dependencies for packages defining ROS messages, simplifying interface development boilerplate.
Requires-Dist: ros-rosidl-generator-py~=0.24.2
Requires-Dist: ros-rosidl-runtime-c~=4.9.5
Requires-Dist: ros-rosidl-typesupport-introspection-c~=4.9.5
Requires-Dist: ros-rosidl-typesupport-fastrtps-c~=3.8.1
Requires-Dist: ros-rosidl-typesupport-cpp~=3.3.3
Requires-Dist: ros-rosidl-typesupport-c~=3.3.3
Requires-Dist: ros-rosidl-typesupport-fastrtps-cpp~=3.8.1
Requires-Dist: ros-rosidl-runtime-cpp~=4.9.5
Requires-Dist: ros-rosidl-typesupport-introspection-cpp~=4.9.5
Dynamic: description
Dynamic: description-content-type
Dynamic: requires-dist
Dynamic: summary
